warag/__init__.py
warag/__main__.py
warag/__version__.py
warag/cli.py
warag-0.0.0a0.dist-info/LICENSE
warag-0.0.0a0.dist-info/METADATA
warag-0.0.0a0.dist-info/WHEEL
warag-0.0.0a0.dist-info/entry_points.txt
warag-0.0.0a0.dist-info/top_level.txt
warag-0.0.0a0.dist-info/RECORD
