Metadata-Version: 2.1
Name: warag
Version: 0.0.0a0
Home-page: https://github.com/Florents-Tselai/warag
Author: Florents Tselai
License: BSD License
Project-URL: Issues, https://github.com/Florents-Tselai/warag/issues
Project-URL: CI, https://github.com/Florents-Tselai/warag/actions
Project-URL: Changelog, https://github.com/Florents-Tselai/warag/releases
Requires-Python: >=3.11
License-File: LICENSE
Requires-Dist: llm
Requires-Dist: click
Requires-Dist: setuptools
Requires-Dist: pip
Requires-Dist: warcdb
Provides-Extra: test
Requires-Dist: pytest ; extra == 'test'
Requires-Dist: pytest-cov ; extra == 'test'
Requires-Dist: black ; extra == 'test'
Requires-Dist: ruff ; extra == 'test'
